{
"type": "FeatureCollection",
"crs": { "type": "name", "properties": { "name": "urn:ogc:def:crs:OGC:1.3:CRS84" } },
"features": [
{ "type": "Feature", "properties": { "Id": 0 }, "geometry": { "type": "Point", "coordinates": [ -119.35670648852813, 45.699607482796935 ] } },
{ "type": "Feature", "properties": { "Id": 0 }, "geometry": { "type": "Point", "coordinates": [ -119.47092061680799, 45.711028895624921 ] } },
{ "type": "Feature", "properties": { "Id": 0 }, "geometry": { "type": "Point", "coordinates": [ -119.40381981644357, 45.830953730318761 ] } },
{ "type": "Feature", "properties": { "Id": 0 }, "geometry": { "type": "Point", "coordinates": [ -119.68078907752222, 45.759569900143859 ] } },
{ "type": "Feature", "properties": { "Id": 0 }, "geometry": { "type": "Point", "coordinates": [ -119.72361937562717, 45.739582427694884 ] } },
{ "type": "Feature", "properties": { "Id": 0 }, "geometry": { "type": "Point", "coordinates": [ -119.16682550026287, 45.583965677913582 ] } },
{ "type": "Feature", "properties": { "Id": 0 }, "geometry": { "type": "Point", "coordinates": [ -119.00549804406759, 45.705318189210928 ] } },
{ "type": "Feature", "properties": { "Id": 0 }, "geometry": { "type": "Point", "coordinates": [ -118.95838471615215, 45.893771500872681 ] } },
{ "type": "Feature", "properties": { "Id": 0 }, "geometry": { "type": "Point", "coordinates": [ -119.4580715273765, 45.53828002660164 ] } },
{ "type": "Feature", "properties": { "Id": 0 }, "geometry": { "type": "Point", "coordinates": [ -119.34956810551064, 45.524003260566658 ] } },
{ "type": "Feature", "properties": { "Id": 0 }, "geometry": { "type": "Point", "coordinates": [ -118.52579870529223, 45.651066478277997 ] } },
{ "type": "Feature", "properties": { "Id": 0 }, "geometry": { "type": "Point", "coordinates": [ -118.60717627169163, 45.588248707724077 ] } },
{ "type": "Feature", "properties": { "Id": 0 }, "geometry": { "type": "Point", "coordinates": [ -118.7042582807295, 45.509726494531677 ] } },
{ "type": "Feature", "properties": { "Id": 0 }, "geometry": { "type": "Point", "coordinates": [ -118.92412047766821, 45.461185490012745 ] } },
{ "type": "Feature", "properties": { "Id": 0 }, "geometry": { "type": "Point", "coordinates": [ -118.94268027351369, 45.622512946208033 ] } },
{ "type": "Feature", "properties": { "Id": 0 }, "geometry": { "type": "Point", "coordinates": [ -118.35876054268294, 45.82381534730127 ] } },
{ "type": "Feature", "properties": { "Id": 0 }, "geometry": { "type": "Point", "coordinates": [ -118.27167226986955, 45.909475943511161 ] } }
]
}
